fastapi_authentication/__init__.py
fastapi_authentication/con.py
fastapi_authentication/config.py
fastapi_authentication/main.py
fastapi_authentication/models.py
fastapi_authentication/routes/auth_with_otp.py
fastapi_authentication/schemas.py
fastapi_authentication/services/email.py
fastapi_authentication/services/security.py
fastapi_authentication-0.1.1.dist-info/METADATA
fastapi_authentication-0.1.1.dist-info/WHEEL
fastapi_authentication-0.1.1.dist-info/RECORD
